src/__init__.py
src/date_extraction.py
src/main.py
trufflepig-0.11.dist-info/LICENSE
trufflepig-0.11.dist-info/METADATA
trufflepig-0.11.dist-info/WHEEL
trufflepig-0.11.dist-info/top_level.txt
trufflepig-0.11.dist-info/RECORD
