Metadata-Version: 2.1
Name: trufflepig
Version: 0.11
Summary: A python package for rooting around your filesystem
Home-page: https://github.com/chrispcharlton/trufflepig
Author: Chris Charlton, Hector Cubillos
Author-email: chrispcharlton@gmail.com
License: UNKNOWN
Platform: UNKNOWN
Classifier: Programming Language :: Python :: 3
Classifier: License :: OSI Approved :: GNU General Public License v3 or later (GPLv3+)
Classifier: Operating System :: OS Independent
Requires-Python: >=3.6
Requires-Dist: python-dateutil
